README.rst
setup.py
buster/__init__.py
buster/_version.py
buster/buster.py
buster.egg-info/PKG-INFO
buster.egg-info/SOURCES.txt
buster.egg-info/dependency_links.txt
buster.egg-info/entry_points.txt
buster.egg-info/requires.txt
buster.egg-info/top_level.txt