Metadata-Version: 1.0
Name: buster
Version: 0.1.1
Summary: Static site generator for Ghost and Github
Home-page: https://github.com/axitkhurana/buster
Author: Akshit Khurana
Author-email: axitkhurana@gmail.com
License: MIT
Platform: UNKNOWN
